valvesmd/__init__.py
valvesmd/classes.py
valvesmd/parser.py
valvesmd/smd.py
valvesmd/utils.py
valvesmd/writer.py
valvesmd-1.0.2.dist-info/LICENSE.txt
valvesmd-1.0.2.dist-info/METADATA
valvesmd-1.0.2.dist-info/WHEEL
valvesmd-1.0.2.dist-info/top_level.txt
valvesmd-1.0.2.dist-info/RECORD
